Metadata-Version: 2.1
Name: new-edamino
Version: 1.1
Summary: Library for Amino.
Home-page: https://github.com/LucasAlgerDay/amino.li
Author: Lucas
Author-email: lucasday173@gmail.com
License: MIT
Keywords: aminoapps,edamino,amino,amino-bot,narvii,api,python,python3,python3.x
Requires-Python: >=3.6
